QuadraticElement/QAE.py
QuadraticElement/QE.py
QuadraticElement/__init__.py
QuadraticElement/_library.py
QuadraticElement/_open.py
QuadraticElement/new_user.py
QuadraticElement/user_message.py
QuadraticElement-0.0.5.4.1.dist-info/LICENSE.txt
QuadraticElement-0.0.5.4.1.dist-info/METADATA
QuadraticElement-0.0.5.4.1.dist-info/WHEEL
QuadraticElement-0.0.5.4.1.dist-info/top_level.txt
QuadraticElement-0.0.5.4.1.dist-info/RECORD
