Metadata-Version: 2.1
Name: QuadraticElement
Version: 0.0.5.4.1
Summary: 命令行项目
Home-page: https://codechina.csdn.net/qq_53280175/quadraticelement
Author: PYmili
Author-email: mc2005wj@163.com
Maintainer: PYmili
Maintainer-email: mc2005wj@163.com
License: MIT License
Platform: UNKNOWN
Classifier: Operating System :: OS Independent
Classifier: Natural Language :: Chinese (Simplified)
Classifier: License :: OSI Approved :: MIT License
Classifier: Programming Language :: Python :: 3.8
Classifier: Programming Language :: Python :: 3.9
Classifier: Topic :: Software Development :: Libraries
Requires-Python: >=3.8
License-File: LICENSE.txt
Requires-Dist: FastDataTime (>=0.0.8)
Requires-Dist: RandomKey (>=0.0.1)
Requires-Dist: numpy (>=1.21.2)
Requires-Dist: wget (>=3.2)
Requires-Dist: opencv-python (>=4.5.3.56)
Requires-Dist: PyPoli (>=0.1.0)
Requires-Dist: FolderProcessing (>=0.1.1.2)
